{"cameraMode":{"drawMode":0,"name":"Shaded","section":"Shading Mode"},"sceneLighting":true,"audioPlay":false,"sceneViewState":{"m_AlwaysRefresh":false,"showFog":true,"showSkybox":true,"showFlares":true,"showImageEffects":true,"showParticleSystems":true,"showVisualEffectGraphs":true,"m_FxEnabled":true},"in2DMode":false,"pivot":{"x":5.5,"y":-2.8500003814697267,"z":-1.3000001907348633},"rotation":{"x":0.20029668509960175,"y":0.0138373002409935,"z":-0.006848288234323263,"w":0.9796156287193298},"size":10.508543968200684,"orthographic":false}